

{
  "itemIdentifier": "cdif.bbr.metadata.cdifProperties.cdifProv",
  "$schema": "metaschema.yaml",
  "name": "CDIF Provenance Activity",
  "abstract": "Extended provenance activity for CDIF metadata, adding schema.org Action properties (agents, instruments, methodology, temporal bounds, action chaining) to the base prov:Activity.",
  "status": "under-development",
  "dateTimeAddition": "2026-02-24T00:00:00Z",
  "itemClass": "schema",
  "register": "cdif-building-block-register",
  "version": "0.1",
  "dateOfLastChange": "2026-02-24",
  "link": "https://github.com/usgin/metadataBuildingBlocks",
  "maturity": "draft",
  "scope": "unstable",
  "tags": [
    "CDIF",
    "provenance",
    "prov",
    "action",
    "methodology"
  ],
  "sources": [
    {
      "title": "ODIS Provenance Recommendations",
      "link": "https://book.odis.org/thematics/provenance/README.html"
    },
    {
      "title": "schema.org Action",
      "link": "https://schema.org/Action"
    }
  ],
  "shaclShapes": {
    "cdif.bbr.metadata.schemaorgProperties.identifier": [
      "https://usgin.github.io/metadataBuildingBlocks/_sources/schemaorgProperties/identifier/rules.shacl"
    ],
    "cdif.bbr.metadata.schemaorgProperties.additionalProperty": [
      "https://usgin.github.io/metadataBuildingBlocks/_sources/schemaorgProperties/additionalProperty/rules.shacl"
    ],
    "cdif.bbr.metadata.schemaorgProperties.definedTerm": [
      "https://usgin.github.io/metadataBuildingBlocks/_sources/schemaorgProperties/definedTerm/rules.shacl"
    ],
    "cdif.bbr.metadata.schemaorgProperties.agentInRole": [
      "https://usgin.github.io/metadataBuildingBlocks/_sources/schemaorgProperties/agentInRole/rules.shacl"
    ],
    "cdif.bbr.metadata.schemaorgProperties.person": [
      "https://usgin.github.io/metadataBuildingBlocks/_sources/schemaorgProperties/person/rules.shacl"
    ],
    "cdif.bbr.metadata.schemaorgProperties.organization": [
      "https://usgin.github.io/metadataBuildingBlocks/_sources/schemaorgProperties/organization/rules.shacl"
    ],
    "cdif.bbr.metadata.provProperties.generatedBy": [
      "https://usgin.github.io/metadataBuildingBlocks/_sources/provProperties/generatedBy/rules.shacl"
    ],
    "cdif.bbr.metadata.schemaorgProperties.labeledLink": [
      "https://usgin.github.io/metadataBuildingBlocks/_sources/schemaorgProperties/labeledLink/rules.shacl"
    ],
    "cdif.bbr.metadata.schemaorgProperties.spatialExtent": [
      "https://usgin.github.io/metadataBuildingBlocks/_sources/schemaorgProperties/spatialExtent/rules.shacl"
    ]
  },
  "dependsOn": [
    "cdif.bbr.metadata.schemaorgProperties.identifier",
    "cdif.bbr.metadata.schemaorgProperties.additionalProperty",
    "cdif.bbr.metadata.schemaorgProperties.agentInRole",
    "cdif.bbr.metadata.provProperties.generatedBy",
    "cdif.bbr.metadata.schemaorgProperties.definedTerm",
    "cdif.bbr.metadata.schemaorgProperties.labeledLink",
    "cdif.bbr.metadata.schemaorgProperties.person",
    "cdif.bbr.metadata.schemaorgProperties.organization",
    "cdif.bbr.metadata.schemaorgProperties.spatialExtent"
  ],
  "schema": {
    "application/yaml": "https://usgin.github.io/metadataBuildingBlocks/build/annotated/bbr/metadata/cdifProperties/cdifProv/schema.yaml",
    "application/json": "https://usgin.github.io/metadataBuildingBlocks/build/annotated/bbr/metadata/cdifProperties/cdifProv/schema.json"
  },
  "sourceSchema": "https://usgin.github.io/metadataBuildingBlocks/_sources/cdifProperties/cdifProv/schema.yaml",
  "ldContext": "https://usgin.github.io/metadataBuildingBlocks/build/annotated/bbr/metadata/cdifProperties/cdifProv/context.jsonld",
  "sourceFiles": "https://usgin.github.io/metadataBuildingBlocks/_sources/cdifProperties/cdifProv/",
  "rdfData": [],
  "validationPassed": true,
  "annotatedSchema": "$schema: https://json-schema.org/draft/2020-12/schema\ntitle: CDIF Provenance Activity\ndescription: Extended provenance activity building block for CDIF. Extends the minimal\n  prov:Activity (generatedBy) with schema.org Action properties for comprehensive\n  provenance documentation including agents, instruments, methodology, temporal bounds,\n  action chaining, and more.\ntype: object\nallOf:\n- $ref: https://usgin.github.io/metadataBuildingBlocks/build/annotated/bbr/metadata/provProperties/generatedBy/schema.yaml\n- type: object\n  properties:\n    schema:name:\n      type: string\n      description: Human-readable name for the activity\n    schema:description:\n      type: string\n      description: Text description of what this activity did\n    schema:identifier:\n      description: Formal identifier for this activity\n      anyOf:\n      - $ref: '#/$defs/Identifier'\n      - type: string\n    schema:agent:\n      description: Primary responsible agent for this activity (maps to PROV wasAssociatedWith)\n      anyOf:\n      - $ref: '#/$defs/Person'\n      - $ref: '#/$defs/Organization'\n      - $ref: '#/$defs/AgentInRole'\n      - type: object\n        properties:\n          '@id':\n            type: string\n            description: reference to an agent defined elsewhere\n    schema:participant:\n      description: Other participants in this activity\n      type: array\n      items:\n        anyOf:\n        - $ref: '#/$defs/Person'\n        - $ref: '#/$defs/Organization'\n        - $ref: '#/$defs/AgentInRole'\n        - type: object\n          properties:\n            '@id':\n              type: string\n              description: reference to a participant defined elsewhere\n    schema:instrument:\n      description: Tools, software, sensors, or instruments used in this activity\n      type: array\n      items:\n        anyOf:\n        - $ref: '#/$defs/DefinedTerm'\n        - $ref: '#/$defs/LabeledLink'\n        - type: string\n        - type: object\n          properties:\n            '@id':\n              type: string\n              description: reference to an instrument defined elsewhere\n    schema:object:\n      description: Input entity for this activity (for action chaining, references\n        the result of a prior activity)\n      anyOf:\n      - type: string\n      - type: object\n        properties:\n          '@id':\n            type: string\n            description: reference to an input entity\n    schema:result:\n      description: Output entity produced by this activity (for action chaining, can\n        be referenced as object of a subsequent activity)\n      anyOf:\n      - type: string\n      - type: object\n        properties:\n          '@id':\n            type: string\n            description: reference to an output entity\n    schema:actionStatus:\n      type: string\n      description: Status of this activity\n      enum:\n      - schema:CompletedActionStatus\n      - schema:ActiveActionStatus\n      - schema:PotentialActionStatus\n      - schema:FailedActionStatus\n    schema:startTime:\n      type: string\n      description: ISO8601 date-time when the activity started (maps to PROV startedAtTime)\n    schema:endTime:\n      type: string\n      description: ISO8601 date-time when the activity ended (maps to PROV endedAtTime)\n    schema:location:\n      description: Where the activity occurred\n      anyOf:\n      - $ref: '#/$defs/SpatialExtent'\n      - type: string\n      - type: object\n        properties:\n          '@id':\n            type: string\n            description: reference to a place defined elsewhere\n    schema:actionProcess:\n      description: Methodology or protocol for this activity\n      anyOf:\n      - $ref: '#/$defs/HowTo'\n      - type: string\n      - type: object\n        properties:\n          '@id':\n            type: string\n            description: reference to a methodology defined elsewhere\n    schema:error:\n      type: string\n      description: Error description for failed activities\n    schema:additionalProperty:\n      description: Domain-specific extension properties\n      type: array\n      items:\n        $ref: '#/$defs/AdditionalProperty'\n$defs:\n  Person:\n    $ref: https://usgin.github.io/metadataBuildingBlocks/build/annotated/bbr/metadata/schemaorgProperties/person/schema.yaml\n  Organization:\n    $ref: https://usgin.github.io/metadataBuildingBlocks/build/annotated/bbr/metadata/schemaorgProperties/organization/schema.yaml\n  AgentInRole:\n    $ref: https://usgin.github.io/metadataBuildingBlocks/build/annotated/bbr/metadata/schemaorgProperties/agentInRole/schema.yaml\n  Identifier:\n    $ref: https://usgin.github.io/metadataBuildingBlocks/build/annotated/bbr/metadata/schemaorgProperties/identifier/schema.yaml\n  DefinedTerm:\n    $ref: https://usgin.github.io/metadataBuildingBlocks/build/annotated/bbr/metadata/schemaorgProperties/definedTerm/schema.yaml\n  LabeledLink:\n    $ref: https://usgin.github.io/metadataBuildingBlocks/build/annotated/bbr/metadata/schemaorgProperties/labeledLink/schema.yaml\n  SpatialExtent:\n    $ref: https://usgin.github.io/metadataBuildingBlocks/build/annotated/bbr/metadata/schemaorgProperties/spatialExtent/schema.yaml\n  AdditionalProperty:\n    $ref: https://usgin.github.io/metadataBuildingBlocks/build/annotated/bbr/metadata/schemaorgProperties/additionalProperty/schema.yaml\n  HowTo:\n    type: object\n    description: A methodology or protocol described as a HowTo with optional steps\n    properties:\n      '@type':\n        type: string\n        const: schema:HowTo\n      '@id':\n        type: string\n      schema:name:\n        type: string\n        description: Name of the methodology or protocol\n      schema:description:\n        type: string\n        description: Description of the methodology\n      schema:url:\n        type: string\n        format: uri\n        description: URL to a published methodology or protocol document\n      schema:step:\n        type: array\n        description: Ordered steps in this methodology\n        items:\n          $ref: '#/$defs/HowToStep'\n    required:\n    - '@type'\n    anyOf:\n    - required:\n      - schema:name\n    - required:\n      - schema:url\n  HowToStep:\n    type: object\n    description: A single step in a HowTo methodology\n    properties:\n      '@type':\n        type: string\n        const: schema:HowToStep\n      schema:name:\n        type: string\n        description: Name of this step\n      schema:description:\n        type: string\n        description: Description of what this step involves\n      schema:url:\n        type: string\n        format: uri\n        description: URL to documentation for this step\n      schema:position:\n        type: integer\n        description: Ordinal position of this step\n    required:\n    - '@type'\n    - schema:name\n  Claim:\n    type: object\n    description: A statement or assertion about the dataset, such as a quality claim\n    properties:\n      '@type':\n        type: string\n        const: schema:Claim\n      '@id':\n        type: string\n      schema:claimReviewed:\n        type: string\n        description: The claim being reviewed or asserted\n      schema:author:\n        description: Author of this claim\n        anyOf:\n        - $ref: '#/$defs/Person'\n        - $ref: '#/$defs/Organization'\n        - type: object\n          properties:\n            '@id':\n              type: string\n      schema:datePublished:\n        type: string\n        description: ISO8601 date when this claim was published\n      schema:appearance:\n        description: Where this claim appears\n        anyOf:\n        - type: string\n        - $ref: '#/$defs/LabeledLink'\n    required:\n    - '@type'\n    - schema:claimReviewed\n",
  "gitRepository": "https://github.com/usgin/metadataBuildingBlocks",
  "gitPath": "_sources/cdifProperties/cdifProv"
}